lotr_ryankubin/__init__.py
lotr_ryankubin/config.py
lotr_ryankubin/connection.py
lotr_ryankubin/lotr.py
lotr_ryankubin/movie.py
lotr_ryankubin/query.py
lotr_ryankubin/quote.py
lotr_ryankubin/schemas.py
lotr_ryankubin-0.1.1.dist-info/METADATA
lotr_ryankubin-0.1.1.dist-info/WHEEL
lotr_ryankubin-0.1.1.dist-info/licenses/LICENSE
lotr_ryankubin-0.1.1.dist-info/RECORD
