Metadata-Version: 2.1
Name: lotr_ryankubin
Version: 0.1.1
Summary: SDK for a lotr API
Project-URL: Homepage, https://github.com/ryankubin/ryan_kubin-SDK
Project-URL: Bug Tracker, https://github.com/ryankubin/ryan_kubin-SDK/issues
Author-email: Ryan Kubin <ryankubin@gmail.com>
License-File: LICENSE
Classifier: License :: OSI Approved :: MIT License
Classifier: Operating System :: OS Independent
Classifier: Programming Language :: Python :: 3
Requires-Python: >=3.7
Requires-Dist: requests
Requires-Dist: urllib3
